{
  "scraped_at": "2026-06-15T10:58:36.949323-07:00",
  "event_count": 97,
  "sources": [
    "DoTheBay",
    "DowntownSF",
    "FunCheap",
    "Luma",
    "Meetup"
  ],
  "events": [
    {
      "title": "World Cup Live",
      "description": "",
      "venue": "",
      "neighborhood": "San Francisco",
      "category": "culture",
      "start_time": "2026-06-15T10:58:24.814224-07:00",
      "price": "Free",
      "url": "https://downtownsf.org/do/world-cup-live",
      "source": "DowntownSF",
      "image_url": "",
      "id": "2e7d01285ae9"
    },
    {
      "title": "SF Pride Celebration",
      "description": "",
      "venue": "Jun",
      "neighborhood": "San Francisco",
      "category": "culture",
      "start_time": "2026-06-15T10:58:24.815323-07:00",
      "price": "Free",
      "url": "https://downtownsf.org/do/sf-pride-celebration",
      "source": "DowntownSF",
      "image_url": "",
      "id": "b0cd63ba5ae6"
    },
    {
      "title": "Stern Grove Festival 2026 Golden Ticket Giveaway",
      "description": "",
      "venue": "Stern Grove",
      "neighborhood": "San Francisco",
      "category": "music",
      "start_time": "2026-06-15T10:58:36.911751-07:00",
      "price": "See listing",
      "url": "https://dothebay.com/events/2026/6/14/stern-grove-festival-2026-golden-ticket-giveaway-tickets",
      "source": "DoTheBay",
      "image_url": "",
      "id": "a5f7e163c049"
    },
    {
      "title": "Life in Space",
      "description": "",
      "venue": "Exploratorium",
      "neighborhood": "San Francisco",
      "category": "culture",
      "start_time": "2026-06-15T10:58:36.913952-07:00",
      "price": "See listing",
      "url": "https://dothebay.com/events/2026/6/11/life-in-space-exploratorium-tickets",
      "source": "DoTheBay",
      "image_url": "",
      "id": "5025dce0d404"
    },
    {
      "title": "Neal Francis",
      "description": "",
      "venue": "Lagunitas Brewing Company",
      "neighborhood": "San Francisco",
      "category": "music",
      "start_time": "2026-06-15T10:58:36.915552-07:00",
      "price": "See listing",
      "url": "https://dothebay.com/events/2026/6/15/neal-francis-live-at-lagunitas-tickets",
      "source": "DoTheBay",
      "image_url": "",
      "id": "ec729db84fc8"
    },
    {
      "title": "Arj Barker",
      "description": "",
      "venue": "Punch Line San Francisco",
      "neighborhood": "Financial District",
      "category": "comedy",
      "start_time": "2026-06-15T10:58:36.916999-07:00",
      "price": "See listing",
      "url": "https://dothebay.com/events/2026/6/15/arj-barker-tickets",
      "source": "DoTheBay",
      "image_url": "",
      "id": "42f34cb352c4"
    },
    {
      "title": "Jane Remover",
      "description": "",
      "venue": "The Regency Ballroom",
      "neighborhood": "Mid-Market",
      "category": "music",
      "start_time": "2026-06-15T10:58:36.918590-07:00",
      "price": "See listing",
      "url": "https://dothebay.com/events/2026/6/15/jane-remover-tickets",
      "source": "DoTheBay",
      "image_url": "",
      "id": "65f8d06e19f3"
    },
    {
      "title": "Bobby McFerrin & MOTION: Circlesongs",
      "description": "",
      "venue": "The Freight",
      "neighborhood": "San Francisco",
      "category": "music",
      "start_time": "2026-06-15T10:58:36.920179-07:00",
      "price": "See listing",
      "url": "https://dothebay.com/events/weekly/mon/bobby-mcferrin-motion-circlesongs-tickets",
      "source": "DoTheBay",
      "image_url": "",
      "id": "9b3aab943543"
    },
    {
      "title": "PIER 39 Soccer Watch Parties",
      "description": "",
      "venue": "PIER 39",
      "neighborhood": "San Francisco",
      "category": "culture",
      "start_time": "2026-06-15T10:58:36.921804-07:00",
      "price": "See listing",
      "url": "https://dothebay.com/events/2026/6/12/pier39-soccer-watch-parties",
      "source": "DoTheBay",
      "image_url": "",
      "id": "a33bb07b0f7f"
    },
    {
      "title": "The Etruscans: From the Heart of Ancient Italy",
      "description": "",
      "venue": "Legion of Honor",
      "neighborhood": "Lincoln Park",
      "category": "art",
      "start_time": "2026-06-15T10:58:36.923371-07:00",
      "price": "See listing",
      "url": "https://dothebay.com/events/2026/5/2/the-etruscans-from-the-heart-of-ancient-italy-tickets",
      "source": "DoTheBay",
      "image_url": "",
      "id": "09960cb2c6d9"
    },
    {
      "title": "Value Select",
      "description": "",
      "venue": "Cafe du Nord",
      "neighborhood": "San Francisco",
      "category": "music",
      "start_time": "2026-06-15T10:58:36.924788-07:00",
      "price": "See listing",
      "url": "https://dothebay.com/events/2026/6/15/value-select-tickets",
      "source": "DoTheBay",
      "image_url": "",
      "id": "db6f4800f24e"
    },
    {
      "title": "French Montana & Max B",
      "description": "",
      "venue": "The Midway",
      "neighborhood": "Dogpatch",
      "category": "music",
      "start_time": "2026-06-15T10:58:36.926209-07:00",
      "price": "See listing",
      "url": "https://dothebay.com/events/2026/6/15/wave-gods-narcos-tour-french-montana-and-max-b-tickets",
      "source": "DoTheBay",
      "image_url": "",
      "id": "e4d4d14017c7"
    },
    {
      "title": "Haight Laughsbury Comedy Show",
      "description": "",
      "venue": "O'Reilly's Pub",
      "neighborhood": "Haight-Ashbury",
      "category": "comedy",
      "start_time": "2026-06-15T10:58:36.927978-07:00",
      "price": "See listing",
      "url": "https://dothebay.com/events/weekly/mon/let-em-cook-a-fully-improvised-standup-comedy-show-tickets",
      "source": "DoTheBay",
      "image_url": "",
      "id": "ddbfc15dc52f"
    },
    {
      "title": "Docent Tours: The Etruscans",
      "description": "",
      "venue": "Legion of Honor",
      "neighborhood": "Lincoln Park",
      "category": "culture",
      "start_time": "2026-06-15T10:58:36.929537-07:00",
      "price": "See listing",
      "url": "https://dothebay.com/events/2026/5/7/docent-tours-the-etruscans-tickets",
      "source": "DoTheBay",
      "image_url": "",
      "id": "82ec6cd64f2a"
    },
    {
      "title": "Total Accord Festival 2026",
      "description": "",
      "venue": "Various Locations",
      "neighborhood": "San Francisco",
      "category": "music",
      "start_time": "2026-06-15T10:58:36.930677-07:00",
      "price": "See listing",
      "url": "https://dothebay.com/events/2026/6/3/total-accord-festival-2026-tickets",
      "source": "DoTheBay",
      "image_url": "",
      "id": "30c164cb9cf5"
    },
    {
      "title": "Legacy Society Lecture + Tea",
      "description": "",
      "venue": "Legion of Honor",
      "neighborhood": "Lincoln Park",
      "category": "culture",
      "start_time": "2026-06-15T10:58:36.932248-07:00",
      "price": "See listing",
      "url": "https://dothebay.com/events/2026/6/15/legacy-society-lecture-tea-tickets",
      "source": "DoTheBay",
      "image_url": "",
      "id": "fe12d2f3c210"
    },
    {
      "title": "Golden State Valkyries vs. Los Angeles Sparks",
      "description": "",
      "venue": "Chase Center",
      "neighborhood": "Mission Bay",
      "category": "sports",
      "start_time": "2026-06-15T10:58:36.933662-07:00",
      "price": "See listing",
      "url": "https://dothebay.com/events/2026/6/15/golden-state-valkyries-vs-los-angeles-sparks-tickets",
      "source": "DoTheBay",
      "image_url": "",
      "id": "9bfb0b828f42"
    },
    {
      "title": "Sir Woman",
      "description": "",
      "venue": "Felton Music Hall",
      "neighborhood": "San Francisco",
      "category": "music",
      "start_time": "2026-06-15T10:58:36.934774-07:00",
      "price": "See listing",
      "url": "https://dothebay.com/events/2026/6/15/sir-woman-tickets",
      "source": "DoTheBay",
      "image_url": "",
      "id": "1bab7beca1e4"
    },
    {
      "title": "Spark Social SF Watch Parties",
      "description": "",
      "venue": "SPARK Social SF",
      "neighborhood": "San Francisco",
      "category": "culture",
      "start_time": "2026-06-15T10:58:36.936077-07:00",
      "price": "See listing",
      "url": "https://dothebay.com/events/2026/6/12/spark-social-sf-watch-parties-tickets",
      "source": "DoTheBay",
      "image_url": "",
      "id": "5777705d5158"
    },
    {
      "title": "The Autocollants, Rob & Jay, Devoted Fans",
      "description": "",
      "venue": "Bottom Of The Hill",
      "neighborhood": "Potrero Hill",
      "category": "music",
      "start_time": "2026-06-15T10:58:36.937679-07:00",
      "price": "See listing",
      "url": "https://dothebay.com/events/2026/6/15/the-autocollants-rob-jay-devoted-fans-tickets",
      "source": "DoTheBay",
      "image_url": "",
      "id": "bcac9cebc54f"
    },
    {
      "title": "Thrive City Soccer Viewings",
      "description": "",
      "venue": "Thrive City",
      "neighborhood": "San Francisco",
      "category": "culture",
      "start_time": "2026-06-15T10:58:36.938972-07:00",
      "price": "See listing",
      "url": "https://dothebay.com/events/2026/6/12/thrive-city-soccer-viewings-tickets",
      "source": "DoTheBay",
      "image_url": "",
      "id": "6d925fca5925"
    },
    {
      "title": "Summer Soccer Watch Party",
      "description": "",
      "venue": "Mission Rock",
      "neighborhood": "Mission",
      "category": "culture",
      "start_time": "2026-06-15T10:58:36.940633-07:00",
      "price": "See listing",
      "url": "https://dothebay.com/events/2026/6/13/summer-soccer-watch-party-tickets",
      "source": "DoTheBay",
      "image_url": "",
      "id": "c4242a226399"
    },
    {
      "title": "Chess Night at Barebottle Brewery",
      "description": "",
      "venue": "BAREBOTTLE BREWING CO.",
      "neighborhood": "San Francisco",
      "category": "outdoor",
      "start_time": "2026-06-15T10:58:36.941854-07:00",
      "price": "See listing",
      "url": "https://dothebay.com/events/weekly/mon/chess-night-at-barebottle-brewery-tickets",
      "source": "DoTheBay",
      "image_url": "",
      "id": "1392fa289b90"
    },
    {
      "title": "Joey Alexander",
      "description": "",
      "venue": "Yoshi's Oakland",
      "neighborhood": "San Francisco",
      "category": "music",
      "start_time": "2026-06-15T10:58:36.943449-07:00",
      "price": "See listing",
      "url": "https://dothebay.com/events/2026/6/15/joey-alexander-tickets",
      "source": "DoTheBay",
      "image_url": "",
      "id": "385618bf042e"
    },
    {
      "title": "Leon G. Ray's Lingerie Soiree",
      "description": "",
      "venue": "DNA Lounge",
      "neighborhood": "SoMa",
      "category": "music",
      "start_time": "2026-06-15T10:58:36.944938-07:00",
      "price": "See listing",
      "url": "https://dothebay.com/events/2026/6/15/leon-g-ray-s-lingerie-soiree-tickets",
      "source": "DoTheBay",
      "image_url": "",
      "id": "37e7b8b9d55f"
    },
    {
      "title": "Freakyoke Karaoke",
      "description": "",
      "venue": "Thee Stork Club",
      "neighborhood": "San Francisco",
      "category": "music",
      "start_time": "2026-06-15T10:58:36.946204-07:00",
      "price": "See listing",
      "url": "https://dothebay.com/events/2026/6/15/freakyoke-karaoke-6-15-tickets",
      "source": "DoTheBay",
      "image_url": "",
      "id": "dae99d63bc96"
    },
    {
      "title": "Mirthquake: Monday Live Comedy in the Richmond",
      "description": "",
      "venue": "The Abbey Tavern",
      "neighborhood": "Richmond",
      "category": "comedy",
      "start_time": "2026-06-15T10:58:36.947745-07:00",
      "price": "See listing",
      "url": "https://dothebay.com/events/weekly/mon/mirthquake-monday-live-comedy-in-the-richmond-tickets",
      "source": "DoTheBay",
      "image_url": "",
      "id": "5eca24ca440d"
    },
    {
      "title": "Taste of Asia 2026 - San Francisco",
      "description": "",
      "venue": "",
      "neighborhood": "San Francisco",
      "category": "culture",
      "start_time": "2026-06-15T18:30:00.000Z",
      "price": "See listing",
      "url": "https://luma.com/38ddve7c",
      "source": "Luma",
      "image_url": "",
      "id": "6f8f02168e57"
    },
    {
      "title": "Filipino Mahjong at Mr. Mahjong's",
      "description": "",
      "venue": "Mr. Mahjong's",
      "neighborhood": "San Francisco",
      "category": "culture",
      "start_time": "2026-06-15T19:00:00-07:00",
      "price": "Free",
      "url": "https://downtownsf.org/do/filipino-mahjong-at-mr-mahjongs",
      "source": "DowntownSF",
      "image_url": "",
      "id": "fb66e885e403"
    },
    {
      "title": "The fast lane",
      "description": "",
      "venue": "",
      "neighborhood": "San Francisco",
      "category": "culture",
      "start_time": "2026-06-16T00:00:00.000Z",
      "price": "See listing",
      "url": "https://luma.com/chalk-data26",
      "source": "Luma",
      "image_url": "",
      "id": "8ece5a022e85"
    },
    {
      "title": "Compile 2026 Opening Party",
      "description": "",
      "venue": "",
      "neighborhood": "San Francisco",
      "category": "art",
      "start_time": "2026-06-16T01:00:00.000Z",
      "price": "See listing",
      "url": "https://luma.com/88e4g1zi",
      "source": "Luma",
      "image_url": "",
      "id": "993c695e0959"
    },
    {
      "title": "FALCON FANTASIA",
      "description": "",
      "venue": "",
      "neighborhood": "San Francisco",
      "category": "culture",
      "start_time": "2026-06-16T01:00:00.000Z",
      "price": "See listing",
      "url": "https://luma.com/u0fiw8ei",
      "source": "Luma",
      "image_url": "",
      "id": "e3457f5d9e7e"
    },
    {
      "title": "BioTech and Pharma Startups, Investors & Professionals Networking Event",
      "description": "**✨ To join this event, please make sure to book your ticket here 👉[https://www.eventbrite.com/e/1988826210734?aff=oddtdtcreator](https://www.eventbrite.com/e/1988826210734?aff=oddtdtcreator)** **Spaces are limited, and only registered guests with a ticket will be able to attend. Don’t miss out!** J",
      "venue": "Noc Noc",
      "neighborhood": "San Francisco",
      "category": "tech",
      "start_time": "2026-06-16T02:00:00.000Z",
      "price": "See listing",
      "url": "https://www.meetup.com/sanfrancisco-startup-pitch-and-networking/events/314641774/",
      "source": "Meetup",
      "image_url": "/images/fallbacks/redesign/group-cover-4-square.webp",
      "id": "0255b484dec8"
    },
    {
      "title": "ClickHouse Cafe @ Data & AI Summit",
      "description": "",
      "venue": "",
      "neighborhood": "San Francisco",
      "category": "tech",
      "start_time": "2026-06-16T15:00:00.000Z",
      "price": "See listing",
      "url": "https://luma.com/clickh-vrjd",
      "source": "Luma",
      "image_url": "",
      "id": "ae359a793775"
    },
    {
      "title": "Stripe Startups Build Day San Francisco—featuring Wen Sang, co-founder/COO of Genspark",
      "description": "",
      "venue": "",
      "neighborhood": "San Francisco",
      "category": "art",
      "start_time": "2026-06-16T16:30:00.000Z",
      "price": "See listing",
      "url": "https://luma.com/cli3p75t",
      "source": "Luma",
      "image_url": "",
      "id": "66977a1a0793"
    },
    {
      "title": "Xochipilli Dance Company",
      "description": "",
      "venue": "12pm - 2pm",
      "neighborhood": "San Francisco",
      "category": "culture",
      "start_time": "2026-06-16T19:00:00-07:00",
      "price": "Free",
      "url": "https://downtownsf.org/do/xochipilli-dance-company",
      "source": "DowntownSF",
      "image_url": "",
      "id": "c6bab1b75776"
    },
    {
      "title": "Teaching Tuesday",
      "description": "",
      "venue": "5:30pm - 8:30pm",
      "neighborhood": "San Francisco",
      "category": "culture",
      "start_time": "2026-06-16T19:00:00-07:00",
      "price": "Free",
      "url": "https://downtownsf.org/do/teaching-tuesday-mahjong-night-with-cindy",
      "source": "DowntownSF",
      "image_url": "",
      "id": "761e004af678"
    },
    {
      "title": "Creating Queer Third Spaces",
      "description": "",
      "venue": "7pm - 8:30pm",
      "neighborhood": "San Francisco",
      "category": "culture",
      "start_time": "2026-06-16T19:00:00-07:00",
      "price": "Free",
      "url": "https://downtownsf.org/do/creating-queer-third-spaces-envisioning-places-to-connect-and-belong",
      "source": "DowntownSF",
      "image_url": "",
      "id": "ab7cb5a6bf65"
    },
    {
      "title": "Comedy Allstars",
      "description": "",
      "venue": "The Punch Line",
      "neighborhood": "Financial District",
      "category": "comedy",
      "start_time": "2026-06-16T19:00:00-07:00",
      "price": "Free",
      "url": "https://downtownsf.org/do/comedy-allstars",
      "source": "DowntownSF",
      "image_url": "",
      "id": "ae0cd16c2ee3"
    },
    {
      "title": "Codex Community Meetup - San Francisco",
      "description": "",
      "venue": "",
      "neighborhood": "San Francisco",
      "category": "culture",
      "start_time": "2026-06-17T00:00:00.000Z",
      "price": "See listing",
      "url": "https://luma.com/codex-jun16-2026",
      "source": "Luma",
      "image_url": "",
      "id": "322cb19d453f"
    },
    {
      "title": "Foundry Live Demo Night",
      "description": "",
      "venue": "",
      "neighborhood": "San Francisco",
      "category": "culture",
      "start_time": "2026-06-17T00:00:00.000Z",
      "price": "See listing",
      "url": "https://luma.com/56wimzrk",
      "source": "Luma",
      "image_url": "",
      "id": "955794e0d52a"
    },
    {
      "title": "Generating Cre(ai)tivity with AI Snack Club",
      "description": "",
      "venue": "",
      "neighborhood": "San Francisco",
      "category": "tech",
      "start_time": "2026-06-17T00:00:00.000Z",
      "price": "See listing",
      "url": "https://luma.com/aisnack-9u6o",
      "source": "Luma",
      "image_url": "",
      "id": "f934d99d0dcc"
    },
    {
      "title": "Mahjong Party for AI Builders",
      "description": "",
      "venue": "",
      "neighborhood": "San Francisco",
      "category": "art",
      "start_time": "2026-06-17T00:00:00.000Z",
      "price": "See listing",
      "url": "https://luma.com/i04pq9o1",
      "source": "Luma",
      "image_url": "",
      "id": "5c75f100e4d7"
    },
    {
      "title": "The Agent Stack: Lightning Talks + Happy Hour with Pioneer & Exa",
      "description": "",
      "venue": "",
      "neighborhood": "San Francisco",
      "category": "lectures",
      "start_time": "2026-06-17T01:00:00.000Z",
      "price": "See listing",
      "url": "https://luma.com/r0sjpnhd",
      "source": "Luma",
      "image_url": "",
      "id": "8b824ffb1fbe"
    },
    {
      "title": "Jazz on the Plaz(a) with La Familia Latin Jazz Trio",
      "description": "",
      "venue": "Mechanics Monument Plaza",
      "neighborhood": "San Francisco",
      "category": "music",
      "start_time": "2026-06-17T19:00:00-07:00",
      "price": "Free",
      "url": "https://downtownsf.org/do/jazz-on-the-plaza-with-la-familia-latin-jazz-trio",
      "source": "DowntownSF",
      "image_url": "",
      "id": "2dfadd9e9571"
    },
    {
      "title": "Reading Group (+🧋): JUDGMENTBENCH: Comparing Rubric and Preference Evaluation for Quality Assessment",
      "description": "",
      "venue": "",
      "neighborhood": "San Francisco",
      "category": "lectures",
      "start_time": "2026-06-17T22:00:00.000Z",
      "price": "See listing",
      "url": "https://luma.com/qwsxqfa2",
      "source": "Luma",
      "image_url": "",
      "id": "7858ae0d4c9b"
    },
    {
      "title": "Full Sail Deploy",
      "description": "",
      "venue": "",
      "neighborhood": "San Francisco",
      "category": "culture",
      "start_time": "2026-06-18T00:30:00.000Z",
      "price": "See listing",
      "url": "https://luma.com/bpjek2ac",
      "source": "Luma",
      "image_url": "",
      "id": "5f3bfc68bdf5"
    },
    {
      "title": "Make It Mean Something: A Panel for SF Creatives",
      "description": "",
      "venue": "",
      "neighborhood": "San Francisco",
      "category": "lectures",
      "start_time": "2026-06-18T00:30:00.000Z",
      "price": "See listing",
      "url": "https://luma.com/rugjqpj7",
      "source": "Luma",
      "image_url": "",
      "id": "6db884fc8b92"
    },
    {
      "title": "Punk Software Hack Night: Build Tools That Work for You",
      "description": "",
      "venue": "",
      "neighborhood": "San Francisco",
      "category": "tech",
      "start_time": "2026-06-18T00:30:00.000Z",
      "price": "See listing",
      "url": "https://luma.com/Punk1",
      "source": "Luma",
      "image_url": "",
      "id": "6eb9fd70549e"
    },
    {
      "title": "Artificially Unintelligent: SF Tech Comedy Show (June)",
      "description": "",
      "venue": "",
      "neighborhood": "San Francisco",
      "category": "comedy",
      "start_time": "2026-06-18T02:00:00.000Z",
      "price": "See listing",
      "url": "https://luma.com/SFTechComedyJune",
      "source": "Luma",
      "image_url": "",
      "id": "06a12efc74f4"
    },
    {
      "title": "Mixer & Networking Meetup",
      "description": "This is a great opportunity to meet new people and make new connections. Feel free to bring a friend or join solo. Everyone is welcome. The location will be updated based on the RSVP numbers. Please DM if you have any questions. Come network with us!",
      "venue": "Afterwork Bar",
      "neighborhood": "San Francisco",
      "category": "culture",
      "start_time": "2026-06-18T02:00:00.000Z",
      "price": "See listing",
      "url": "https://www.meetup.com/sf-social-mixers-and-networking/events/314835176/",
      "source": "Meetup",
      "image_url": "/images/fallbacks/redesign/group-cover-4-square.webp",
      "id": "9dc142b2b54e"
    },
    {
      "title": "for the eldest daughters only",
      "description": "",
      "venue": "",
      "neighborhood": "San Francisco",
      "category": "culture",
      "start_time": "2026-06-18T02:30:00.000Z",
      "price": "See listing",
      "url": "https://luma.com/e3m35brt",
      "source": "Luma",
      "image_url": "",
      "id": "b63633d8131c"
    },
    {
      "title": "Agentic Engineering Summit",
      "description": "",
      "venue": "",
      "neighborhood": "San Francisco",
      "category": "culture",
      "start_time": "2026-06-18T16:00:00.000Z",
      "price": "See listing",
      "url": "https://luma.com/agentsummit",
      "source": "Luma",
      "image_url": "",
      "id": "c24c92142c43"
    },
    {
      "title": "Render localhost:2026 SF",
      "description": "",
      "venue": "",
      "neighborhood": "San Francisco",
      "category": "culture",
      "start_time": "2026-06-18T16:00:00.000Z",
      "price": "See listing",
      "url": "https://luma.com/localhost-2026-sf",
      "source": "Luma",
      "image_url": "",
      "id": "ba74ff7227bc"
    },
    {
      "title": "Walking Tour",
      "description": "",
      "venue": "11am - 1pm",
      "neighborhood": "San Francisco",
      "category": "outdoor",
      "start_time": "2026-06-18T19:00:00-07:00",
      "price": "Free",
      "url": "https://downtownsf.org/do/walking-tour-cityscapes-and-public-spaces",
      "source": "DowntownSF",
      "image_url": "",
      "id": "72e6f0cbc3aa"
    },
    {
      "title": "Downtown Jukebox with DJ Chris Go",
      "description": "",
      "venue": "Landing at Leidesdorff",
      "neighborhood": "San Francisco",
      "category": "nightlife",
      "start_time": "2026-06-18T19:00:00-07:00",
      "price": "Free",
      "url": "https://downtownsf.org/do/downtown-jukebox-with-dj-chris-go-1",
      "source": "DowntownSF",
      "image_url": "",
      "id": "b4546d120bb9"
    },
    {
      "title": "Chess on the Plaza",
      "description": "",
      "venue": "Mechanics Monument Plaza",
      "neighborhood": "San Francisco",
      "category": "culture",
      "start_time": "2026-06-18T19:00:00-07:00",
      "price": "Free",
      "url": "https://downtownsf.org/do/chess-on-the-plaza-2",
      "source": "DowntownSF",
      "image_url": "",
      "id": "4a90c55167fd"
    },
    {
      "title": "How to get press without a PR agency: a workshop for early-stage founders",
      "description": "",
      "venue": "",
      "neighborhood": "San Francisco",
      "category": "theater",
      "start_time": "2026-06-18T19:00:00.000Z",
      "price": "See listing",
      "url": "https://luma.com/fqvmt1ha",
      "source": "Luma",
      "image_url": "",
      "id": "2b2a7e3cfe7b"
    },
    {
      "title": "World Cup Watch Party - Mexico vs South Korea",
      "description": "Get ready for an exciting World Cup showdown as Mexico takes on South Korea on June 18th at 6PM! We'll be gathering inside a lively bar to watch the match live on big screens with great drinks, high energy, and fellow soccer fans. Expect a fun atmosphere full of cheering, reactions, friendly banter,",
      "venue": "Curio",
      "neighborhood": "San Francisco",
      "category": "sports",
      "start_time": "2026-06-19T00:30:00.000Z",
      "price": "See listing",
      "url": "https://www.meetup.com/baysocials/events/315209207/",
      "source": "Meetup",
      "image_url": "/images/fallbacks/redesign/group-cover-1-square.webp",
      "id": "059dee1ac77b"
    },
    {
      "title": "Exploratorium After Dark: Unplug and Play",
      "description": "Meet us at Pier 15. No kids allowed—but feel free to act like one. Get inquisitive, grab a drink, unplug and play with 700+ interactive exhibits exploring science, art, and perception. Journey through total darkness in the Exploratorium's twisting, turning, world-famous Tactile Dome. With 75,000 squ",
      "venue": "Exploratorium",
      "neighborhood": "San Francisco",
      "category": "art",
      "start_time": "2026-06-19T01:00:00.000Z",
      "price": "See listing",
      "url": "https://www.meetup.com/bay-area-millennials-and-gen-z-meetup-group/events/313894744/",
      "source": "Meetup",
      "image_url": "/images/fallbacks/redesign/group-cover-4-square.webp",
      "id": "e5373e9fac27"
    },
    {
      "title": "Drag Me Downtown",
      "description": "",
      "venue": "4:30pm - 7pm",
      "neighborhood": "San Francisco",
      "category": "nightlife",
      "start_time": "2026-06-19T19:00:00-07:00",
      "price": "Free",
      "url": "https://downtownsf.org/do/drag-me-downtown-pride-pop-up-drag-shows",
      "source": "DowntownSF",
      "image_url": "",
      "id": "79f2ddf63109"
    },
    {
      "title": " Fort Mason Night Market Social ",
      "description": "**RSVP via:** https://app.gistirl.com/event-details/87EPksaHpKzPiyOdDhHu **Early Bird Discounts | More $ Later** Sizzling grills, the scent of toasted spices in the cool air, and a crowd of fellow food lovers ready to feast. Spend an hour in quick one-on-one rounds, then grab your favorite people an",
      "venue": "Great Meadow Park at Fort Mason",
      "neighborhood": "Marina",
      "category": "food",
      "start_time": "2026-06-20T01:00:00.000Z",
      "price": "See listing",
      "url": "https://www.meetup.com/gist-irl/events/314896324/",
      "source": "Meetup",
      "image_url": "/images/fallbacks/redesign/group-cover-4-square.webp",
      "id": "e22db37430a4"
    },
    {
      "title": "Queer History Tour",
      "description": "",
      "venue": "11am - 12:30pm",
      "neighborhood": "San Francisco",
      "category": "culture",
      "start_time": "2026-06-20T19:00:00-07:00",
      "price": "Free",
      "url": "https://downtownsf.org/do/unspeakable-vice-queer-history-tour",
      "source": "DowntownSF",
      "image_url": "",
      "id": "e476877cb675"
    },
    {
      "title": "Discover SF -- North Beach Festival, SF ",
      "description": "Come with us to discover another **cultural** neighborhood of San Francisco. The 72nd North Beach Festival is to be held in the heart of the historic **North Beach** neighborhood, on Father's day weekend. It is one of the **signature** neighborhood festivals in San Francisco and is generally conside",
      "venue": "Reveille coffee co.",
      "neighborhood": "San Francisco",
      "category": "outdoor",
      "start_time": "2026-06-20T20:00:00.000Z",
      "price": "See listing",
      "url": "https://www.meetup.com/townflame/events/313663064/",
      "source": "Meetup",
      "image_url": "/images/fallbacks/redesign/group-cover-2-square.webp",
      "id": "7b88833cdf09"
    },
    {
      "title": "Singles Mingle @ Decodance in SF FREE ENTRY 21&UP",
      "description": "You guys, we're going back to DecoDance in SF! **DecoDance is pure swank and class!** 🍸✨ Think amazing cocktails, delicious food, cozy couches, gorgeous décor you’ll fall in love with, and an all-around vibey atmosphere. This hidden gem on the side of Polk Street is truly something special. Last tim",
      "venue": "Decodance Bar-Lounge",
      "neighborhood": "San Francisco",
      "category": "food",
      "start_time": "2026-06-21T02:00:00.000Z",
      "price": "See listing",
      "url": "https://www.meetup.com/singles-mingle-getting-people-together/events/314367069/",
      "source": "Meetup",
      "image_url": "/images/fallbacks/redesign/group-cover-4-square.webp",
      "id": "e606ba80a125"
    },
    {
      "title": "Daybreaker",
      "description": "",
      "venue": "10am - 1pm",
      "neighborhood": "San Francisco",
      "category": "culture",
      "start_time": "2026-06-21T19:00:00-07:00",
      "price": "Free",
      "url": "https://downtownsf.org/do/daybreaker-san-francisco",
      "source": "DowntownSF",
      "image_url": "",
      "id": "fc4919944e80"
    },
    {
      "title": "San Francisco Tech Connect: Startups, Investors, Professionals Networking",
      "description": "**✨ To join this event, please make sure to book your ticket here 👉[https://www.eventbrite.com/e/1989219723742?aff=oddtdtcreatorr](https://www.eventbrite.com/e/1989219723742?aff=oddtdtcreator)** **Spaces are limited, and only registered guests with a ticket will be able to attend. Don’t miss out!** ",
      "venue": "Casements Bar",
      "neighborhood": "San Francisco",
      "category": "tech",
      "start_time": "2026-06-23T02:00:00.000Z",
      "price": "See listing",
      "url": "https://www.meetup.com/sanfrancisco-startup-pitch-and-networking/events/314736472/",
      "source": "Meetup",
      "image_url": "/images/fallbacks/redesign/group-cover-4-square.webp",
      "id": "b0a536a8e685"
    },
    {
      "title": "Ice Cream Social with Daniel Riera & Daniel Berkman",
      "description": "",
      "venue": "Mechanics Monument Plaza",
      "neighborhood": "San Francisco",
      "category": "culture",
      "start_time": "2026-06-23T19:00:00-07:00",
      "price": "Free",
      "url": "https://downtownsf.org/do/ice-cream-social-with-daniel-riera-daniel-berkman",
      "source": "DowntownSF",
      "image_url": "",
      "id": "3c2e13a89b85"
    },
    {
      "title": "SF Pride",
      "description": "",
      "venue": "10am - 7pm",
      "neighborhood": "San Francisco",
      "category": "culture",
      "start_time": "2026-06-25T19:00:00-07:00",
      "price": "Free",
      "url": "https://downtownsf.org/do/4th-annual-human-rights-summit",
      "source": "DowntownSF",
      "image_url": "",
      "id": "467df79c92de"
    },
    {
      "title": "Ashlyn So",
      "description": "",
      "venue": "5:30pm - 7:30pm",
      "neighborhood": "San Francisco",
      "category": "culture",
      "start_time": "2026-06-25T19:00:00-07:00",
      "price": "Free",
      "url": "https://downtownsf.org/do/ashlyn-so-recolored-collection-exhibition",
      "source": "DowntownSF",
      "image_url": "",
      "id": "46e03d4858fc"
    },
    {
      "title": "Dunites Wines x Verjus",
      "description": "",
      "venue": "Verjus",
      "neighborhood": "San Francisco",
      "category": "food",
      "start_time": "2026-06-25T19:00:00-07:00",
      "price": "Free",
      "url": "https://downtownsf.org/do/dunites-wines-x-verjus",
      "source": "DowntownSF",
      "image_url": "",
      "id": "1d102f18e093"
    },
    {
      "title": "Deep Dive Conversation: Self-Compassion: Being on Your Own Side",
      "description": "How do you talk to yourself when no one is listening? What does your inner voice say when you make a mistake, fall short, or feel like you're failing? Join us for this month's Deep Dive Conversation as we explore Self-Compassion. A real practiced and revolutionary way of relating to yourself. In thi",
      "venue": "",
      "neighborhood": "San Francisco",
      "category": "lectures",
      "start_time": "2026-06-26T02:00:00.000Z",
      "price": "See listing",
      "url": "https://www.meetup.com/the-la-curiosity-collective-inner-work-self-discovery/events/314694418/",
      "source": "Meetup",
      "image_url": "/images/fallbacks/redesign/group-cover-2-square.webp",
      "id": "2aa74724babd"
    },
    {
      "title": "WELCOME",
      "description": "",
      "venue": "Embarcadero Plaza",
      "neighborhood": "Embarcadero",
      "category": "culture",
      "start_time": "2026-06-26T19:00:00-07:00",
      "price": "Free",
      "url": "https://downtownsf.org/do/welcome",
      "source": "DowntownSF",
      "image_url": "",
      "id": "f2cce6867745"
    },
    {
      "title": "Most Best Open Mic",
      "description": "",
      "venue": "KALW",
      "neighborhood": "San Francisco",
      "category": "culture",
      "start_time": "2026-06-26T19:00:00-07:00",
      "price": "Free",
      "url": "https://downtownsf.org/do/most-best-open-mic-1",
      "source": "DowntownSF",
      "image_url": "",
      "id": "3e4245db7e07"
    },
    {
      "title": "Singles Speed Dating at Polly Ann Ice Cream",
      "description": "",
      "venue": "Polly Ann Ice Cream",
      "neighborhood": "San Francisco",
      "category": "culture",
      "start_time": "2026-06-26T19:00:00-07:00",
      "price": "Free",
      "url": "https://downtownsf.org/do/singles-speed-dating-at-polly-ann-ice-cream",
      "source": "DowntownSF",
      "image_url": "",
      "id": "d22cf2f062b3"
    },
    {
      "title": "Solidarity Cinema",
      "description": "",
      "venue": "KALW",
      "neighborhood": "San Francisco",
      "category": "film",
      "start_time": "2026-06-26T19:00:00-07:00",
      "price": "Free",
      "url": "https://downtownsf.org/do/solidarity-cinema",
      "source": "DowntownSF",
      "image_url": "",
      "id": "26502be70c74"
    },
    {
      "title": "Peoples March and Trans Ally Rally",
      "description": "",
      "venue": "Embarcadero Plaza",
      "neighborhood": "Embarcadero",
      "category": "culture",
      "start_time": "2026-06-27T19:00:00-07:00",
      "price": "Free",
      "url": "https://downtownsf.org/do/peoples-march-and-trans-ally-rally",
      "source": "DowntownSF",
      "image_url": "",
      "id": "ff8ed1607423"
    },
    {
      "title": "SF Pride Parade with the Corgis",
      "description": "",
      "venue": "",
      "neighborhood": "San Francisco",
      "category": "culture",
      "start_time": "2026-06-28T19:00:00-07:00",
      "price": "Free",
      "url": "https://downtownsf.org/do/march-with-everyone-loves-a-corgi-at-the-pride-parade",
      "source": "DowntownSF",
      "image_url": "",
      "id": "4d09f94bb706"
    },
    {
      "title": "Pride Parade Watch Party",
      "description": "",
      "venue": "Avotoasty",
      "neighborhood": "San Francisco",
      "category": "art",
      "start_time": "2026-06-28T19:00:00-07:00",
      "price": "Free",
      "url": "https://downtownsf.org/do/pride-parade-watch-party",
      "source": "DowntownSF",
      "image_url": "",
      "id": "983b8649f3a0"
    },
    {
      "title": "SF Pride Parade",
      "description": "",
      "venue": "",
      "neighborhood": "San Francisco",
      "category": "culture",
      "start_time": "2026-06-28T19:00:00-07:00",
      "price": "Free",
      "url": "https://downtownsf.org/do/sf-pride-parade",
      "source": "DowntownSF",
      "image_url": "",
      "id": "f1fed8fe9f3e"
    },
    {
      "title": "SF Brunch Social: Make New Friends",
      "description": "⚠️ **IMPORTANT: You must sign up and buy a ticket here to attend:** [https://groupvibe.com/](https://groupvibe.com/) **Join the San Francisco Brunch Club and make new friends!** Each meetup brings together 4–6 people for casual conversations over brunch. We use the Groupvibe platform to facilitate t",
      "venue": "Secret Restaurant Location in San Francisco,",
      "neighborhood": "San Francisco",
      "category": "food",
      "start_time": "2026-06-28T19:30:00.000Z",
      "price": "See listing",
      "url": "https://www.meetup.com/meetup-group-psuvhuqa/events/314845531/",
      "source": "Meetup",
      "image_url": "/images/fallbacks/redesign/group-cover-5-square.webp",
      "id": "7d019bfc4426"
    },
    {
      "title": "20s & 30s Speed Friending : Emporium + Madrones Monday Night Groove!!",
      "description": "**RSVP via:** https://app.gistirl.com/event-details/77Gi10iOoa4oA09Cm2SK **Early Bird Discounts | More $ Later** OKAY! You all have spoken!! So here we go for our next event: Picture this: you walk up to the Emporium on a Monday night for their famous \"Industry Night,\" and see some new faces, some o",
      "venue": "Emporium SF - Arcade Bar Venue",
      "neighborhood": "San Francisco",
      "category": "outdoor",
      "start_time": "2026-06-30T02:30:00.000Z",
      "price": "See listing",
      "url": "https://www.meetup.com/gist-irl/events/314764472/",
      "source": "Meetup",
      "image_url": "/images/fallbacks/redesign/group-cover-4-square.webp",
      "id": "254b4bae7649"
    },
    {
      "title": "Market Street Pack Walk",
      "description": "",
      "venue": "",
      "neighborhood": "San Francisco",
      "category": "outdoor",
      "start_time": "2026-07-02T19:00:00-07:00",
      "price": "Free",
      "url": "https://downtownsf.org/do/market-street-pack-walk",
      "source": "DowntownSF",
      "image_url": "",
      "id": "d9eec6c385b0"
    },
    {
      "title": "El Cerrito’s WorldOne Festival “Tardeada” Pre-Party - FREE",
      "description": "The post El Cerrito’s WorldOne Festival “Tardeada” Pre-Party appeared first on Funcheap .",
      "venue": "",
      "neighborhood": "San Francisco",
      "category": "art",
      "start_time": "2026-07-03T19:00:00-07:00",
      "price": "Free",
      "url": "https://sf.funcheap.com/el-cerritos-worldone-festival-tardeada-pre-party/",
      "source": "FunCheap",
      "image_url": "",
      "id": "84c3c6348d64"
    },
    {
      "title": "El Cerrito’s Annual WorldOne Festival 2025 (July 3-4) - FREE",
      "description": "The post El Cerrito’s Annual WorldOne Festival 2025 (July 3-4) appeared first on Funcheap .",
      "venue": "",
      "neighborhood": "San Francisco",
      "category": "culture",
      "start_time": "2026-07-04T19:00:00-07:00",
      "price": "Free",
      "url": "https://sf.funcheap.com/el-cerritos-annual-worldone-festival-2025-july-3-4/",
      "source": "FunCheap",
      "image_url": "",
      "id": "e6996499b744"
    },
    {
      "title": "Martinez | Hometown 4th of July Parade & Fireworks | 2026 - FREE",
      "description": "SATURDAY, JulY 4, 2026 – 10am Join us for a patriotic extravaganza at the Annual Downtown Martinez 4th of July Parade, proudly presented by Martinez Refining Company. It’s time to paint Main Street red, white, and blue as over 40 spirited entries march down the heart ... The post Martinez | Hometown",
      "venue": "",
      "neighborhood": "San Francisco",
      "category": "art",
      "start_time": "2026-07-04T19:00:00-07:00",
      "price": "Free",
      "url": "https://sf.funcheap.com/hometown-4th-july-celebration-fireworks-martinez/",
      "source": "FunCheap",
      "image_url": "",
      "id": "32fc53be975f"
    },
    {
      "title": "Concord | 4th of July Parade, Concert & Fireworks | 2026 - FREE",
      "description": "2026 Schedule of Events Events at Todos Santos Plaza 8:00 am : Stars & Stripes Kids Fun Run 8:00 am : Rotary Pancake Breakfast 8:15 am : Stars & Stripes 5k Run & Walk 10:00 am : Independence Day Parade Events at Mt. Diablo High School 4:00 PM : Festival Gates Open 5:30 ... The post Concord | 4th of ",
      "venue": "",
      "neighborhood": "San Francisco",
      "category": "outdoor",
      "start_time": "2026-07-04T19:00:00-07:00",
      "price": "Free",
      "url": "https://sf.funcheap.com/fourth-july-jubilee-festival-parade-concord/",
      "source": "FunCheap",
      "image_url": "",
      "id": "f0f92c631069"
    },
    {
      "title": "Danville | 4th of July Parade | 2026 - FREE",
      "description": "The Kiwanis-Danville Parade will take place on Saturday, July 4th, 2026 from 9am-noon in downtown Danville, California. Honoring SRVUSD: Great schools + great students = great community! This year’s 2026 Parade Grand Marshal, is San Ramon Valley Unified School District. 2026 marks the 51st anniversa",
      "venue": "",
      "neighborhood": "San Francisco",
      "category": "culture",
      "start_time": "2026-07-04T19:00:00-07:00",
      "price": "Free",
      "url": "https://sf.funcheap.com/kiwanis-july-4th-parade-danville/",
      "source": "FunCheap",
      "image_url": "",
      "id": "9d619157c83e"
    },
    {
      "title": "4th of July Picnic + Fireworks Over the Waterfront",
      "description": "**Please bring something to share with the group, whether it's a favorite dish, dessert, fruit, or beverages.** Celebrate Independence Day with an afternoon and evening of great company, good food, and one of San Francisco's best views! We'll meet at beautiful Francisco Park starting at **5:00 PM** ",
      "venue": "Francisco Park",
      "neighborhood": "San Francisco",
      "category": "outdoor",
      "start_time": "2026-07-05T00:00:00.000Z",
      "price": "See listing",
      "url": "https://www.meetup.com/baysocials/events/315044757/",
      "source": "Meetup",
      "image_url": "/images/fallbacks/redesign/group-cover-1-square.webp",
      "id": "37a19edc0953"
    },
    {
      "title": "HEAD WEST Marketplace",
      "description": "",
      "venue": "Ferry Building",
      "neighborhood": "Embarcadero",
      "category": "culture",
      "start_time": "2026-07-05T19:00:00-07:00",
      "price": "Free",
      "url": "https://downtownsf.org/do/headwest-marketplace",
      "source": "DowntownSF",
      "image_url": "",
      "id": "3cfad75ba679"
    },
    {
      "title": "Breakfast Jams with Violinist Anju Goto",
      "description": "",
      "venue": "Mechanics Monument Plaza",
      "neighborhood": "San Francisco",
      "category": "culture",
      "start_time": "2026-07-07T19:00:00-07:00",
      "price": "Free",
      "url": "https://downtownsf.org/do/breakfast-jams-with-violinist-anju-goto",
      "source": "DowntownSF",
      "image_url": "",
      "id": "5b38ac449293"
    },
    {
      "title": "Jazz on the Plaz(a) with Low End Theory",
      "description": "",
      "venue": "Mechanics Monument Plaza",
      "neighborhood": "San Francisco",
      "category": "music",
      "start_time": "2026-07-08T19:00:00-07:00",
      "price": "Free",
      "url": "https://downtownsf.org/do/jazz-on-the-plaza-with-low-end-theory",
      "source": "DowntownSF",
      "image_url": "",
      "id": "5f928ad4394e"
    },
    {
      "title": "Baroque & Brew",
      "description": "",
      "venue": "10am - 11am",
      "neighborhood": "San Francisco",
      "category": "culture",
      "start_time": "2026-07-10T19:00:00-07:00",
      "price": "Free",
      "url": "https://downtownsf.org/do/free-coffee-concerts-freshly-brewed-baroque",
      "source": "DowntownSF",
      "image_url": "",
      "id": "d6f3ea03ce8a"
    },
    {
      "title": "Ferry Fest",
      "description": "",
      "venue": "Ferry Building",
      "neighborhood": "Embarcadero",
      "category": "culture",
      "start_time": "2026-07-12T19:00:00-07:00",
      "price": "Free",
      "url": "https://downtownsf.org/do/ferry-fest",
      "source": "DowntownSF",
      "image_url": "",
      "id": "261bc4ad81a0"
    },
    {
      "title": "Lunch Rhyme with Radio XII & Damneet Kaur",
      "description": "",
      "venue": "Mechanics Monument Plaza",
      "neighborhood": "San Francisco",
      "category": "culture",
      "start_time": "2026-07-14T19:00:00-07:00",
      "price": "Free",
      "url": "https://downtownsf.org/do/lunch-rhyme-with-radio-xii-and-damneet-kaur",
      "source": "DowntownSF",
      "image_url": "",
      "id": "93186fb955a6"
    },
    {
      "title": "Bastille Day Celebration with Le Jazz Hot Quartet",
      "description": "",
      "venue": "Mechanics' Institute",
      "neighborhood": "San Francisco",
      "category": "music",
      "start_time": "2026-07-14T19:00:00-07:00",
      "price": "Free",
      "url": "https://downtownsf.org/do/bastille-day-celebration-with-le-jazz-hot-quartet",
      "source": "DowntownSF",
      "image_url": "",
      "id": "bb17bf7ea34b"
    },
    {
      "title": "“Manny’s Neighborhood Trash Cleanup” w/ $1 Beer & Free Yoga Classes, Free Fries (SF) - FREE",
      "description": "The post “Manny’s Neighborhood Trash Cleanup” w/ $1 Beer & Free Yoga Classes, Free Fries (SF) appeared first on Funcheap .",
      "venue": "",
      "neighborhood": "San Francisco",
      "category": "food",
      "start_time": "2026-08-09T19:00:00-07:00",
      "price": "$1",
      "url": "https://sf.funcheap.com/mannys-neighborhood-trash-cleanup-w-1-beer-free-yoga-classes-free-fries-sf-144/",
      "source": "FunCheap",
      "image_url": "",
      "id": "670fbfbc8184"
    }
  ]
}